cryptofuzz/CLI.py
cryptofuzz/Wallet.py
cryptofuzz/__init__.py
cryptofuzz/__main__.py
cryptofuzz/assest.py
cryptofuzz/bip39.py
cryptofuzz/block.py
cryptofuzz/bs58.py
cryptofuzz/example.py
cryptofuzz/hd.py
cryptofuzz/utils.py
CryptoFuzz-18.6.0.dist-info/LICENSE
CryptoFuzz-18.6.0.dist-info/METADATA
CryptoFuzz-18.6.0.dist-info/WHEEL
CryptoFuzz-18.6.0.dist-info/entry_points.txt
CryptoFuzz-18.6.0.dist-info/top_level.txt
CryptoFuzz-18.6.0.dist-info/zip-safe
CryptoFuzz-18.6.0.dist-info/RECORD
