Metadata-Version: 2.1
Name: CryptoFuzz
Version: 18.6.0
Summary: Generated and Converted Keys with any Type Foundation from Private Key [WIF Hexed Mnemonic and Binary Bytes seed] in Python
Home-page: https://github.com/Pymmdrza/cryptoFuzz
Author: Mohammadreza (Mmdrza.Com)
Author-email: Pymmdrza@gmail.com
License: MIT
Project-URL: Bug Tracker, https://github.com/Pymmdrza/cryptoFuzz/issues
Project-URL: Documentation, https://cryptofuzz.readthedocs.io/
Project-URL: Source Code, https://github.com/Pymmdrza/cryptoFuzz
Project-URL: Website, https://mmdrza.com
Keywords: CryptoFuzz,Wif,Mnemonic,Binary,seed,Foundation,Private,Key,HEX,Mnemonic,Binary,Bytes,bitcoin,ethereum,tron,dogecoin,zcash,digibyte,bitcoin gold,wallet,bip32,bip39,litecoin,qtum,ravencoin,BTC,ETH,TRX,DOGE,BTG,LTC,ZEC,AXE,DASH
Classifier: Development Status :: 5 - Production/Stable
Classifier: Intended Audience :: Developers
Classifier: Intended Audience :: Information Technology
Classifier: Topic :: Security :: Cryptography
Classifier: License :: OSI Approved :: MIT License
Classifier: Programming Language :: Python :: 3
Classifier: Programming Language :: Python :: 3.6
Classifier: Programming Language :: Python :: 3.7
Classifier: Programming Language :: Python :: 3.8
Classifier: Programming Language :: Python :: 3.9
Classifier: Programming Language :: Python :: 3.10
Classifier: Programming Language :: Python :: 3.11
Classifier: Programming Language :: Python :: Implementation :: CPython
Classifier: Operating System :: OS Independent
License-File: LICENSE
Requires-Dist: hdwallet
Requires-Dist: ecdsa
